MANIFEST.in
README.rst
setup.cfg
setup.py
GBpy/Test_quaternion.py
GBpy/__init__.py
GBpy/__init__.pyc
GBpy/bp_basis.py
GBpy/csl_utility_functions.py
GBpy/find_csl_dsc.py
GBpy/generate_symm_ops.py
GBpy/geometry_tools.py
GBpy/integer_manipulations.py
GBpy/lattice.py
GBpy/misorient_fz.py
GBpy/quaternion.py
GBpy/test_cases.py
GBpy/tools.py
GBpy/vector3d.py
GBpy.egg-info/PKG-INFO
GBpy.egg-info/SOURCES.txt
GBpy.egg-info/dependency_links.txt
GBpy.egg-info/top_level.txt
GBpy/csl_generators/__init__.py
GBpy/csl_generators/csl_dsc_genlattice.py
GBpy/csl_generators/genereate_csl_mats.py
GBpy/csl_generators/matlab_csls/432_CommonCSL.mat
GBpy/csl_generators/prior_lit_csls/hP_Id_lit_csl_common_rotations.pkl
GBpy/csl_generators/prior_lit_csls/hP_ca_lit_csl_specific_rotations.pkl
GBpy/csl_generators/prior_lit_csls/hR_Id_lit_csl_common_rotations.pkl
GBpy/csl_generators/prior_lit_csls/hR_ca_lit_csl_specific_rotations.pkl
GBpy/csl_generators/prior_lit_csls/prior_lit_csls.py
GBpy/csl_generators/prior_lit_csls/tP_Id_lit_csl_common_rotations.pkl
GBpy/csl_generators/prior_lit_csls/tP_ca_lit_csl_specific_rotations.pkl
GBpy/csl_generators/python_csls/cF_Id_csl_common_rotations.pkl
GBpy/csl_generators/python_csls/hP_Id_csl_common_rotations.pkl
GBpy/csl_generators/python_csls/hR_Id_csl_common_rotations.pkl
GBpy/csl_generators/python_csls/tP_Id_csl_common_rotations.pkl
GBpy/csl_generators/python_csls/tP_Id_exp_csl_common_rotations.pkl
GBpy/csl_generators/python_csls/tP_ca_csl_specific_tau_1_9_rotations.pkl
GBpy/csl_generators/test_csls/test_csl_mats_exp.py
GBpy/csl_generators/test_csls/test_cubic_cslmats.py
GBpy/csl_generators/test_csls/test_lit_cslmats.py
GBpy/csl_generators/test_csls/test_rhomb_cslmats.py
GBpy/docs/make.bat
GBpy/docs/build/doctrees/environment.pickle
GBpy/docs/build/doctrees/index.doctree
GBpy/docs/build/html/.buildinfo
GBpy/docs/build/html/genindex.html
GBpy/docs/build/html/index.html
GBpy/docs/build/html/objects.inv
GBpy/docs/build/html/py-modindex.html
GBpy/docs/build/html/search.html
GBpy/docs/build/html/searchindex.js
GBpy/docs/build/html/_modules/bp_basis.html
