Metadata-Version: 1.1
Name: GBpy
Version: 0.1.1
Summary: GBpy is an opensource python package for calculating the geometric properties of interfaces in crystals.
Home-page: https://github.com/adehgha/GBpy
Author: Arash Dehghan Banadaki, Srikanth Patala
Author-email: adehgha@ncsu.edu, spatala@ncsu.edu
License: License :: GNU-GPL
Download-URL: https://github.com/adehgha/GBpy/tarball/0.1.1
Keywords: bicrystallography,interfaces,grain boundaries
Platform: any
Classifier: Development Status :: 2 - Pre-Alpha
Classifier: License :: OSI Approved :: GNU General Public License (GPL)
Classifier: Programming Language :: Python :: 2.6
Classifier: Programming Language :: Python :: 2.7
Classifier: Programming Language :: Python :: 3.0
Classifier: Topic :: Scientific/Engineering :: Mathematics
Classifier: Topic :: Scientific/Engineering :: Physics
Classifier: Topic :: Software Development :: Libraries :: Python Modules
Classifier: Topic :: Utilities
Requires: numpy
Requires: scipy
Requires: setuptools
